stream_web_provider/__init__.py
stream_web_provider/application.py
stream_web_provider/camera_stream.py
stream_web_provider/interruptable_thread.py
stream_web_provider/main.py
stream_web_provider/templates/connecting_camera.png
stream_web_provider/templates/index.html
stream_web_provider/templates/stream_stopped.png
stream_web_provider-0.1.5.dist-info/entry_points.txt
stream_web_provider-0.1.5.dist-info/licenses/LICENSE
stream_web_provider-0.1.5.dist-info/METADATA
stream_web_provider-0.1.5.dist-info/WHEEL
stream_web_provider-0.1.5.dist-info/RECORD
