Metadata-Version: 2.4
Name: stream-web-provider
Version: 0.1.5
Summary: Flask based web video stream provider
License: Apache-2.0
License-File: LICENSE
Author: LukasNebr
Requires-Python: >=3.10,<4.0
Classifier: License :: OSI Approved :: Apache Software License
Classifier: Operating System :: OS Independent
Classifier: Programming Language :: Python :: 3
Classifier: Programming Language :: Python :: 3.10
Classifier: Programming Language :: Python :: 3.11
Classifier: Programming Language :: Python :: 3.12
Classifier: Programming Language :: Python :: 3.13
Classifier: Programming Language :: Python :: 3.14
Requires-Dist: flask
Requires-Dist: opencv-python
Project-URL: homepage, https://github.com/lukasNebr/stream-web-provider
Project-URL: issues, https://github.com/lukasNebr/stream-web-provider/issues
Project-URL: repository, https://github.com/lukasNebr/stream-web-provider
